resolve_module_import.py
resolve_module_import-0.1.0a0.dist-info/licenses/LICENSE
resolve_module_import-0.1.0a0.dist-info/METADATA
resolve_module_import-0.1.0a0.dist-info/WHEEL
resolve_module_import-0.1.0a0.dist-info/top_level.txt
resolve_module_import-0.1.0a0.dist-info/RECORD
