Metadata-Version: 2.4
Name: resolve-module-import
Version: 0.1.0a0
Summary: Resolves a (possibly relative) module import to its fully qualified module name.
Author-email: Jifeng Wu <jifengwu2k@gmail.com>
License-Expression: MIT
Project-URL: Homepage, https://github.com/jifengwu2k/resolve-module-import
Project-URL: Bug Tracker, https://github.com/jifengwu2k/resolve-module-import/issues
Classifier: Programming Language :: Python :: 2
Classifier: Programming Language :: Python :: 3
Classifier: Operating System :: OS Independent
Requires-Python: >=2
License-File: LICENSE
Requires-Dist: typing; python_version < "3.5"
Dynamic: license-file
